eksma_optics_motorized_devices/__init__.py
eksma_optics_motorized_devices/_version.py
eksma_optics_motorized_devices/command.py
eksma_optics_motorized_devices/control.py
eksma_optics_motorized_devices/decimal_with_dimension.py
eksma_optics_motorized_devices/transport.py
eksma_optics_motorized_devices-0.1.3.dist-info/METADATA
eksma_optics_motorized_devices-0.1.3.dist-info/WHEEL
eksma_optics_motorized_devices-0.1.3.dist-info/licenses/LICENSE.txt
eksma_optics_motorized_devices-0.1.3.dist-info/RECORD
